{
  "specialist": "ethics",
  "generated_at": "2026-07-15T14:39:39Z",
  "git_sha": "6e760a7f1e0ee83fe81ff9602239495b27e22519",
  "chunker": {
    "target_tokens_min": 400,
    "target_tokens_max": 900,
    "overlap": "none (structural)",
    "token_estimator": "word+punct count (retrieval/tokens.py)"
  },
  "retrieval_model": "index + fetch/search (FTS5 BM25); no embeddings (TECH_SPEC §8.8)",
  "sqlite": {
    "path": "ethics.sqlite",
    "sha256": "047bc044048df522e11893a32ba28d28724483a012a83bb2cd1052991cf99d90"
  },
  "index": {
    "path": "ethics.index.json",
    "sha256": "260e51029f0e9f9c36690861beb382798ca21b0145b7dec9b9c5376bfc7ad82c"
  },
  "document_count": 17,
  "documents": [
    {
      "doc_id": "23-00122-data61-report-naic-responsibleaitools-web-230620",
      "short_name": "NAIC RAI Tools",
      "title": "Implementing Australia's AI Ethics Principles: A selection of Responsible AI practices and resources",
      "version": "2023",
      "publisher": "CSIRO National AI Centre (prepared by Gradient Institute)",
      "source_url": "https://www.csiro.au/-/media/D61/NAIC/Gradient-Report/23-00122_DATA61_REPORT_NAIC-ResponsibleAITools_WEB_230620.pdf",
      "licence": "CC-BY-SA-4.0",
      "redistributable": true,
      "format": "pdf",
      "sha256": "ae67e49cac327638f85a6b25d628cceff707ad0b9e65790be8b84dd9ed4b1021",
      "page_count": 60,
      "chunk_count": 140
    },
    {
      "doc_id": "2305-12728v1",
      "short_name": "Diversity & Inclusion in AI",
      "title": "Diversity and Inclusion in Artificial Intelligence",
      "version": "v1 (2023)",
      "publisher": "Didar Zowghi and Francesca da Rimini (CSIRO Data61)",
      "source_url": "https://arxiv.org/abs/2305.12728",
      "licence": "arXiv.org perpetual non-exclusive license",
      "redistributable": true,
      "format": "pdf",
      "sha256": "7d8e9f5ca57ede093f1f64b46b97ec1f1a8383377a605f9c492874a357250adf",
      "page_count": 27,
      "chunk_count": 36
    },
    {
      "doc_id": "ahrc-rightstech-2021-final-report-3",
      "short_name": "AHRC HRT Report",
      "title": "Human Rights and Technology Final Report",
      "version": "2021",
      "publisher": "Australian Human Rights Commission",
      "source_url": "https://humanrights.gov.au/our-work/rights-and-freedoms/publications/human-rights-and-technology-final-report-2021",
      "licence": "CC-BY-4.0",
      "redistributable": true,
      "format": "docx",
      "sha256": "65281ec2cdc706e67705a75bd4ed4a841551c5d9e9efb9d0a8da39c7afee9ed2",
      "page_count": null,
      "chunk_count": 256
    },
    {
      "doc_id": "ai-guidance-resource-december-2022",
      "short_name": "AHRC AI Guidance",
      "title": "Artificial Intelligence: guidance resource",
      "version": "December 2022",
      "publisher": "Australian Human Rights Commission",
      "source_url": "https://humanrights.gov.au/our-work/technology-and-human-rights",
      "licence": "CC-BY-4.0",
      "redistributable": true,
      "format": "docx",
      "sha256": "78ab680ebc0a33387f7cfb5a8583ffeb71f944cf9dfe2c2b9b7aeace70fd1b43",
      "page_count": null,
      "chunk_count": 87
    },
    {
      "doc_id": "australia-s-ai-ethics-principles",
      "short_name": "AI Ethics Principles",
      "title": "Australia's AI Ethics Principles",
      "version": "2019",
      "publisher": "Department of Industry, Science and Resources",
      "source_url": "https://www.industry.gov.au/publications/australias-artificial-intelligence-ethics-principles",
      "licence": "CC-BY-4.0",
      "redistributable": true,
      "format": "md",
      "sha256": "5b1b5b2dfe922b1a6269a308190e17dbc834fbb60fb45a084366c067cc0fee7c",
      "page_count": null,
      "chunk_count": 10
    },
    {
      "doc_id": "automated-decision-making-better-practice-guide-march-2025",
      "short_name": "ADM Better Practice Guide",
      "title": "Automated Decision-Making Better Practice Guide",
      "version": "March 2025",
      "publisher": "Commonwealth Ombudsman",
      "source_url": "https://www.ombudsman.gov.au/__data/assets/pdf_file/0025/317437/Automated-Decision-Making-Better-Practice-Guide-March-2025.pdf",
      "licence": "CC-BY-4.0",
      "redistributable": true,
      "format": "pdf",
      "sha256": "fc6b1b6a989128e9351f31d9c80987806e05f09f147dc55cf5005398fbeee2d2",
      "page_count": 61,
      "chunk_count": 121
    },
    {
      "doc_id": "creative-australia-generative-ai-and-creative-work-paper",
      "short_name": "Creative Australia GenAI",
      "title": "Generative AI and creative work – Creative Australia Principles",
      "version": "2024",
      "publisher": "Creative Australia",
      "source_url": "https://creative.gov.au/advocacy-and-research/generative-ai-and-creative-work/",
      "licence": "CC-BY-4.0",
      "redistributable": true,
      "format": "pdf",
      "sha256": "e40cf192468efb06e39743d1efb3f922e1dffc6620b8a4643e3363e16d566073",
      "page_count": 3,
      "chunk_count": 6
    },
    {
      "doc_id": "generative-ai-position-statement-august-2023",
      "short_name": "eSafety GenAI Position Statement",
      "title": "Generative AI – Position Statement",
      "version": "August 2023",
      "publisher": "eSafety Commissioner",
      "source_url": "https://www.esafety.gov.au/industry/tech-trends-and-challenges/generative-ai",
      "licence": "CC-BY-4.0",
      "redistributable": true,
      "format": "pdf",
      "sha256": "50f89f6a2fcf2c501983798a26404ce414d50fe80d1d6fdc01026139e6271b7b",
      "page_count": 40,
      "chunk_count": 55
    },
    {
      "doc_id": "guidance-for-ai-adoption-implementation-guidance-0-0",
      "short_name": "Guidance for AI Adoption",
      "title": "Guidance for AI adoption: implementation guidance",
      "version": "2025",
      "publisher": "National AI Centre",
      "source_url": "https://www.ai.gov.au/staying-safe-and-responsible/essential-ai-practices/guidance-ai-adoption-implementation-guidance",
      "licence": "CC-BY-4.0",
      "redistributable": true,
      "format": "pdf",
      "sha256": "54caf265e5915bf8be6b25572b0938ccfcc540e4804e5f604e651fa1103b82d7",
      "page_count": 50,
      "chunk_count": 88
    },
    {
      "doc_id": "sbd-principles",
      "short_name": "Safety by Design Principles",
      "title": "Safety by Design – Principles",
      "version": "May 2019",
      "publisher": "eSafety Commissioner",
      "source_url": "https://www.esafety.gov.au/sites/default/files/2019-10/SBD%20-%20%20Principles.pdf",
      "licence": "CC-BY-4.0",
      "redistributable": true,
      "format": "pdf",
      "sha256": "142755287468d3393fb9e57a343c7a9e5709c50becf6a314a99cce437b64c90c",
      "page_count": 3,
      "chunk_count": 4
    },
    {
      "doc_id": "trs-guidance-ai-150925",
      "short_name": "TRS AI Guidelines",
      "title": "AI Guidelines",
      "version": "15 September 2025",
      "publisher": "The Research Society",
      "source_url": "https://www.researchsociety.com.au/member-resources/ai-guidelines/",
      "licence": "© The Research Society (member resource)",
      "redistributable": true,
      "format": "pdf",
      "sha256": "3456c2ba0e2b983267a663243417bd26c48059882a2c78fcb288f64f74c7e180",
      "page_count": 15,
      "chunk_count": 37
    },
    {
      "doc_id": "the-new-machinery-of-government-special-report-front-section",
      "short_name": "New Machinery of Government",
      "title": "The new machinery of government: using machine technology in administrative decision-making (front section)",
      "version": "November 2021",
      "publisher": "NSW Ombudsman",
      "source_url": "https://www.ombo.nsw.gov.au/news-and-publications/publications/reports/the-new-machinery-of-government-using-machine-technology-in-administrative-decision-making",
      "licence": "CC-BY-4.0",
      "redistributable": true,
      "format": "pdf",
      "sha256": "3c62a76ee181de0f05194a4474b2cc1037fbdf52fd5ffbc3a777201dfd2a229f",
      "page_count": 105,
      "chunk_count": 220
    },
    {
      "doc_id": "voluntary-ai-safety-standard",
      "short_name": "VAISS",
      "title": "Voluntary AI Safety Standard",
      "version": "2024",
      "publisher": "Department of Industry, Science and Resources",
      "source_url": "https://www.industry.gov.au/publications/voluntary-ai-safety-standard",
      "licence": "CC-BY-4.0",
      "redistributable": true,
      "format": "docx",
      "sha256": "5e0a52777e89ba4ce18749eb34b734a23f3d37915575ea8fa2fb4f4a6be6ee62",
      "page_count": null,
      "chunk_count": 20
    },
    {
      "doc_id": "apo-nid306481",
      "short_name": "ADM Guide (earlier ed.)",
      "title": "Automated decision-making: better practice guide",
      "version": "earlier edition",
      "publisher": "Commonwealth Ombudsman",
      "source_url": "https://apo.org.au/node/306481",
      "licence": "CC-BY-4.0",
      "redistributable": true,
      "format": "pdf",
      "sha256": "e6e4176263c0b0de067567c529dca5811e2630978988e659c33621c0aed9ebf0",
      "page_count": 36,
      "chunk_count": 68
    },
    {
      "doc_id": "co-design-lessons-learned-report",
      "short_name": "Co-Design Lessons Learned",
      "title": "Co-Design Lessons Learned Report",
      "version": "June 2023",
      "publisher": "National Indigenous Australians Agency",
      "source_url": "https://www.niaa.gov.au/sites/default/files/documents/2024-05/co-design-lessons-learned-report.pdf",
      "licence": "CC-BY-4.0",
      "redistributable": true,
      "format": "pdf",
      "sha256": "447382e8e842027a95458a0d1183059657661893d3bd15551c6732981e7f7e6a",
      "page_count": 69,
      "chunk_count": 91
    },
    {
      "doc_id": "framework-governance-indigenous-data",
      "short_name": "Indigenous Data Governance Framework",
      "title": "Framework for Governance of Indigenous Data: Practical guidance for the Australian Public Service",
      "version": "2024",
      "publisher": "National Indigenous Australians Agency",
      "source_url": "https://www.niaa.gov.au/resource-centre/framework-governance-indigenous-data",
      "licence": "CC-BY-4.0",
      "redistributable": true,
      "format": "docx",
      "sha256": "f196997c963f160705b38e125510c1ba1c5a337af1051d16774ababe6cb1a420",
      "page_count": null,
      "chunk_count": 72
    },
    {
      "doc_id": "ltib-report-how-might-ai-affect-trust-ps-delivery",
      "short_name": "LTIB AI & Trust",
      "title": "How might artificial intelligence affect the trustworthiness of public service delivery?",
      "version": "2023",
      "publisher": "Department of the Prime Minister and Cabinet",
      "source_url": "https://www.pmc.gov.au/publications/long-term-insights-briefing",
      "licence": "CC-BY-4.0",
      "redistributable": true,
      "format": "pdf",
      "sha256": "04fe1269ef27ed80d5b40cbcd89ac6d9ee8bbe7767eb4170812cbca503318334",
      "page_count": 43,
      "chunk_count": 59
    }
  ]
}